<?xml version="1.0" encoding="utf-8"?>
<Deployment xmlns="http://schemas.microsoft.com/windowsphone/2009/deployment" AppPlatformVersion="7.1">
  <App xmlns="" ProductID="{dc75005b-d5e6-4458-9fa0-03095cc40938}" Title="GuildWars2CountDown" RuntimeType="Silverlight" Version="1.0.0.0" Genre="apps.normal" Author="GuildWars2CountDown author" Description="Sample description" Publisher="GuildWars2CountDown">
    <IconPath IsRelative="true" IsResource="false">ApplicationIcon.png</IconPath>
    <Capabilities>
      <Capability Name="ID_CAP_GAMERSERVICES" />
      <Capability Name="ID_CAP_IDENTITY_DEVICE" />
      <Capability Name="ID_CAP_IDENTITY_USER" />
      <Capability Name="ID_CAP_LOCATION" />
      <Capability Name="ID_CAP_MEDIALIB" />
      <Capability Name="ID_CAP_MICROPHONE" />
      <Capability Name="ID_CAP_NETWORKING" />
      <Capability Name="ID_CAP_PHONEDIALER" />
      <Capability Name="ID_CAP_PUSH_NOTIFICATION" />
      <Capability Name="ID_CAP_SENSORS" />
      <Capability Name="ID_CAP_WEBBROWSERCOMPONENT" />
      <Capability Name="ID_CAP_ISV_CAMERA" />
      <Capability Name="ID_CAP_CONTACTS" />
      <Capability Name="ID_CAP_APPOINTMENTS" />
    </Capabilities>
    <Tasks>
      <DefaultTask Name="_default" NavigationPage="MainPage.xaml" />
      <ExtendedTask Name="BackgroundTask">
        <BackgroundServiceAgent Specifier="ScheduledTaskAgent" Name="GW2TaskAgent" Source="GW2TaskAgent" Type="GW2TaskAgent.ScheduledAgent" />
      </ExtendedTask>
    </Tasks>
    <Tokens>
      <PrimaryToken TokenID="GuildWars2CountDownToken" TaskName="_default">
        <TemplateType5>
          <BackgroundImageURI IsRelative="true" IsResource="false">Background.png</BackgroundImageURI>
          <Count>0</Count>
          <Title>GW2 Countdown</Title>
        </TemplateType5>
      </PrimaryToken>
    </Tokens>
  </App>
</Deployment>